xmsg/__init__.py
xmsg/xmsg.py
xmsgpy-0.0.1.dist-info/METADATA
xmsgpy-0.0.1.dist-info/WHEEL
xmsgpy-0.0.1.dist-info/top_level.txt
xmsgpy-0.0.1.dist-info/RECORD
