Metadata-Version: 2.1
Name: xmsgpy
Version: 0.0.1
Summary: A package that allows encryption
Home-page: UNKNOWN
Author: Vladimir Valensky
Author-email: 
License: UNKNOWN
Keywords: python,video,stream,video stream,camera stream,sockets
Platform: UNKNOWN
Classifier: Development Status :: 1 - Planning
Classifier: Intended Audience :: Developers
Classifier: Programming Language :: Python :: 3
Classifier: Operating System :: Microsoft :: Windows
Requires-Dist: requests
